[
  {
    "domain": "fasttrackurgentcare.com",
    "analyzed_urls": [
      "https://fasttrackurgentcare.com/",
      "https://fasttrackurgentcare.com/services",
      "https://fasttrackurgentcare.com/emergency"
    ],
    "performance_metrics": {
      "https://fasttrackurgentcare.com/": {
        "mobile": "PSIMetrics(lcp_p75=4.5, inp_p75=350, cls_p75=0.2, fcp_p75=3.0, score=35, device='mobile')",
        "desktop": "PSIMetrics(lcp_p75=4.5, inp_p75=350, cls_p75=0.2, fcp_p75=3.0, score=35, device='desktop')"
      },
      "https://fasttrackurgentcare.com/services": {
        "mobile": "PSIMetrics(lcp_p75=4.5, inp_p75=350, cls_p75=0.2, fcp_p75=3.0, score=35, device='mobile')",
        "desktop": "PSIMetrics(lcp_p75=4.5, inp_p75=350, cls_p75=0.2, fcp_p75=3.0, score=35, device='desktop')"
      },
      "https://fasttrackurgentcare.com/emergency": {
        "mobile": "PSIMetrics(lcp_p75=4.5, inp_p75=350, cls_p75=0.2, fcp_p75=3.0, score=35, device='mobile')",
        "desktop": "PSIMetrics(lcp_p75=4.5, inp_p75=350, cls_p75=0.2, fcp_p75=3.0, score=35, device='desktop')"
      }
    },
    "leak_indicators": [
      "LCP_HIGH",
      "CLS_MODERATE",
      "MOBILE_UNFRIENDLY",
      "INP_MODERATE"
    ],
    "leak_score": 10,
    "evidence_screenshots": [
      "evidence/fasttrackurgentcare.com_20250809_043710_performance.png",
      "evidence/fasttrackurgentcare.com_20250809_043711_performance.png",
      "evidence/fasttrackurgentcare.com_20250809_043711_performance.png"
    ],
    "priority_fixes": [
      "Image optimization + lazy loading (Est. 1.5s LCP improvement)",
      "Mobile responsiveness overhaul (Est. 25% mobile conversion boost)",
      "Image optimization + lazy loading (Est. 1.5s LCP improvement)",
      "Mobile responsiveness overhaul (Est. 25% mobile conversion boost)",
      "Image optimization + lazy loading (Est. 1.5s LCP improvement)",
      "Mobile responsiveness overhaul (Est. 25% mobile conversion boost)"
    ],
    "estimated_impact": "25-40% conversion rate improvement potential",
    "analysis_timestamp": "2025-08-09T07:37:11.822956+00:00"
  },
  {
    "domain": "fasttrackurgentcare.com",
    "analyzed_urls": [
      "https://fasttrackurgentcare.com/",
      "https://fasttrackurgentcare.com/services",
      "https://fasttrackurgentcare.com/emergency"
    ],
    "performance_metrics": {
      "https://fasttrackurgentcare.com/": {
        "mobile": "PSIMetrics(lcp_p75=4.5, inp_p75=350, cls_p75=0.2, fcp_p75=3.0, score=35, device='mobile')",
        "desktop": "PSIMetrics(lcp_p75=4.5, inp_p75=350, cls_p75=0.2, fcp_p75=3.0, score=35, device='desktop')"
      },
      "https://fasttrackurgentcare.com/services": {
        "mobile": "PSIMetrics(lcp_p75=4.5, inp_p75=350, cls_p75=0.2, fcp_p75=3.0, score=35, device='mobile')",
        "desktop": "PSIMetrics(lcp_p75=4.5, inp_p75=350, cls_p75=0.2, fcp_p75=3.0, score=35, device='desktop')"
      },
      "https://fasttrackurgentcare.com/emergency": {
        "mobile": "PSIMetrics(lcp_p75=4.5, inp_p75=350, cls_p75=0.2, fcp_p75=3.0, score=35, device='mobile')",
        "desktop": "PSIMetrics(lcp_p75=4.5, inp_p75=350, cls_p75=0.2, fcp_p75=3.0, score=35, device='desktop')"
      }
    },
    "leak_indicators": [
      "LCP_HIGH",
      "CLS_MODERATE",
      "MOBILE_UNFRIENDLY",
      "INP_MODERATE"
    ],
    "leak_score": 10,
    "evidence_screenshots": [
      "evidence/fasttrackurgentcare.com_20250809_043719_performance.png",
      "evidence/fasttrackurgentcare.com_20250809_043720_performance.png",
      "evidence/fasttrackurgentcare.com_20250809_043720_performance.png"
    ],
    "priority_fixes": [
      "Image optimization + lazy loading (Est. 1.5s LCP improvement)",
      "Mobile responsiveness overhaul (Est. 25% mobile conversion boost)",
      "Image optimization + lazy loading (Est. 1.5s LCP improvement)",
      "Mobile responsiveness overhaul (Est. 25% mobile conversion boost)",
      "Image optimization + lazy loading (Est. 1.5s LCP improvement)",
      "Mobile responsiveness overhaul (Est. 25% mobile conversion boost)"
    ],
    "estimated_impact": "25-40% conversion rate improvement potential",
    "analysis_timestamp": "2025-08-09T07:37:20.601081+00:00"
  }
]